measured/__init__.py
measured/__main__.py
measured/_parser.py
measured/acoustics.py
measured/apocrypha.py
measured/astronomical.py
measured/avoirdupois.py
measured/cli.py
measured/compat.py
measured/computing.py
measured/conversions.py
measured/electronics.py
measured/energy.py
measured/eu.py
measured/fff.py
measured/formatting.py
measured/geometry.py
measured/hypothesis.py
measured/iec.py
measured/iso.py
measured/json.py
measured/metric.py
measured/music.py
measured/natural.py
measured/parsing.py
measured/physics.py
measured/py.typed
measured/pytest.py
measured/si.py
measured/systems.py
measured/troy.py
measured/us.py
measured-0.12.2.dist-info/LICENSE.txt
measured-0.12.2.dist-info/METADATA
measured-0.12.2.dist-info/WHEEL
measured-0.12.2.dist-info/entry_points.txt
measured-0.12.2.dist-info/top_level.txt
measured-0.12.2.dist-info/RECORD
