Metadata-Version: 2.1
Name: measured
Version: 0.12.2
Summary: Fast and Pythonic library for working with measurements and quantities
Home-page: https://github.com/chrisguidry/measured
Author: Chris Guidry
Author-email: chris@theguidrys.us
License: MIT
Project-URL: Bug Tracker, https://github.com/chrisguidry/measured/issues
Classifier: Development Status :: 4 - Beta
Classifier: Intended Audience :: Developers
Classifier: Intended Audience :: Education
Classifier: Intended Audience :: Science/Research
Classifier: License :: OSI Approved :: MIT License
Classifier: Operating System :: OS Independent
Classifier: Programming Language :: Python :: 3
Classifier: Programming Language :: Python :: 3.10
Classifier: Programming Language :: Python :: 3.11
Classifier: Programming Language :: Python :: 3.12
Classifier: Programming Language :: Python :: 3.8
Classifier: Programming Language :: Python :: 3.9
Classifier: Topic :: Scientific/Engineering
Classifier: Topic :: Scientific/Engineering :: Astronomy
Classifier: Topic :: Scientific/Engineering :: Information Analysis
Classifier: Topic :: Scientific/Engineering :: Mathematics
Classifier: Topic :: Scientific/Engineering :: Medical Science Apps.
Classifier: Topic :: Scientific/Engineering :: Physics
Classifier: Topic :: Software Development :: Libraries
Classifier: Topic :: Utilities
Classifier: Typing :: Typed
Requires-Python: >=3.8
License-File: LICENSE.txt
Requires-Dist: typing-extensions ; python_version < "3.9"
Provides-Extra: dev
Requires-Dist: black[jupyter] ; extra == 'dev'
Requires-Dist: build ; extra == 'dev'
Requires-Dist: cloudpickle ; extra == 'dev'
Requires-Dist: fastapi ; extra == 'dev'
Requires-Dist: flake8 ; extra == 'dev'
Requires-Dist: flake8-black ; extra == 'dev'
Requires-Dist: httpx ; extra == 'dev'
Requires-Dist: hypothesis ; extra == 'dev'
Requires-Dist: icecream ; extra == 'dev'
Requires-Dist: isort >=5.12.0 ; extra == 'dev'
Requires-Dist: ipython ; extra == 'dev'
Requires-Dist: jupyter ; extra == 'dev'
Requires-Dist: lark ; extra == 'dev'
Requires-Dist: mkdocs ; extra == 'dev'
Requires-Dist: mkdocs-material ; extra == 'dev'
Requires-Dist: mkdocstrings[python] ; extra == 'dev'
Requires-Dist: mypy ; extra == 'dev'
Requires-Dist: pre-commit ; extra == 'dev'
Requires-Dist: pydantic >2 ; extra == 'dev'
Requires-Dist: pytest ; extra == 'dev'
Requires-Dist: pytest-asyncio ; extra == 'dev'
Requires-Dist: pytest-benchmark ; extra == 'dev'
Requires-Dist: pytest-cov ; extra == 'dev'
Requires-Dist: pytest-xdist ; extra == 'dev'
Requires-Dist: snakeviz ; extra == 'dev'
Requires-Dist: sqlalchemy ; extra == 'dev'
Requires-Dist: tox ; extra == 'dev'
Requires-Dist: typer ; extra == 'dev'
Requires-Dist: tuna ; extra == 'dev'
Requires-Dist: twine ; extra == 'dev'
Requires-Dist: wheel ; extra == 'dev'
Requires-Dist: types-sqlalchemy ; extra == 'dev'
Requires-Dist: memray ; (implementation_name == "cpython" and python_version <= "3.10") and extra == 'dev'
